alexautils/__init__.py
alexautils/logs.py
alexautils/naive_nlg.py
alexautils/pauser.py
alexautils/slot_utils.py
alexautils/ssml_tags.py
alexautils-0.0.1.dist-info/LICENSE.txt
alexautils-0.0.1.dist-info/METADATA
alexautils-0.0.1.dist-info/WHEEL
alexautils-0.0.1.dist-info/top_level.txt
alexautils-0.0.1.dist-info/RECORD
