Metadata-Version: 2.1
Name: alexautils
Version: 0.0.1
Summary: Utility methods to supplement Python ASK SDK
Home-page: https://github.com/jaimiles23/Alexa-Utils
Author: Jai Miles
Author-email: jaimiles23@gmail.com
License: MIT
Keywords: Alexa,ssml,ask sdk
Platform: UNKNOWN
Requires-Dist: ask-sdk-core (==1.11.0)
